README.rst
setup.py
ur1/__init__.py
ur1.egg-info/PKG-INFO
ur1.egg-info/SOURCES.txt
ur1.egg-info/dependency_links.txt
ur1.egg-info/top_level.txt