Metadata-Version: 1.0
Name: ur1
Version: 0.1
Summary: A library to shorten urls with ur1.ca.
Home-page: https://github.com/legoktm/ur1/
Author: Kunal Mehta
Author-email: legoktm@gmail.com
License: Public domain
Platform: UNKNOWN
